[
    {
        "icon": "Link",
        "title": "网站列表",
        "items": [
            [
                {
                    
                    "icon": "Blog",
                    "name": "博客",
                    "url": "https://blog.haoyv.top"
                }, {
                    "icon": "Code",
                    "name": "洛谷",
                    "url": "https://www.luogu.com.cn/"
                }, {
                    "icon": "LogoCodepen",
                    "name": "Atcoder",
                    "url": "https://atcoder.jp/"
                }, {
                    "icon": "Search",
                    "name": "搜索",
                    "url": "https://kaifa.baidu.com/"
                }, {
                    "icon": "CompactDisc",
                    "name": "音乐",
                    "url": "https://music.163.com/"
                }, {
                    "icon": "Cloud",
                    "name": "网盘",
                    "url": "https://pan.baidu.com/"
                }
            ], [
                    {
                    "icon": "Earth",
                    "name": "学习通",
                    "url": "https://i.chaoxing.com/"
                }, {
                    "icon": "Tree",
                    "name": "智慧树",
                    "url": "https://onlineweb.zhihuishu.com/"
                }, {
                    "icon": "School",
                    "name": "优学院",
                    "url": "https://courseweb.ulearning.cn/"
                }, {
                    "icon": "Book",
                    "name": "背单词",
                    "url": "https://kaiyiwing.gitee.io/qwerty-learner/"
                }, {
                    "icon": "Train",
                    "name": "开往",
                    "url": "https://www.foreverblog.cn/go.html"
                }
            ]
        ]
    }, {
        "icon": "Bars",
        "title": "功能列表",
        "items": [
            [
                {
                    "icon": "PencilAlt",
                    "name": "一言",
                    "method": "hitokoto"
                }, {
                    "icon": "SlidersH",
                    "name": "播放器",
                    "method": "player"
                }, {
                    "icon": "Music",
                    "name": "音乐列表",
                    "method": "music"
                }, {
                    "icon": "Cog",
                    "name": "全局设置",
                    "method": "setting"
                }
            ]
        ]
    }
]